{"Confirmation Bias": ["making waves in the industry", "commitment to sustainable and environmentally friendly fishing practices"], "Positive Bias": ["well-established fishing business", "Leading the Way", "reputable companies"], "Authority Bias": ["state-of-the-art sustainable nets and tracking systems"], "Social Desirability Bias": ["sustainable and environmentally friendly fishing practices", "promote sustainable fishing practices"], "Lack of Objectivity": ["Leading the Way", "well-established fishing business"], "Emotional Bias": ["making waves in the industry"]}