{"Confirmation Bias": ["an affirmation of its commitment", "highlighting their dedication"], "Positive Bias": ["environmentally friendly", "sustainable fishing practices", "responsible and legal fishing practices"], "Authority Bias": ["with other industry leaders", "a local fishing leader"], "Lack of Objectivity": ["The company has recently invested $2000", "an affirmation of its commitment"], "Emotional Bias": ["environmentally friendly", "sustainable fishing practices"], "Social Desirability Bias": ["sustainable fishing practices", "responsible and legal fishing practices"], "Information Bias": ["The company has recently invested $2000", "multiple transactions with various companies"]}