{"Positive Bias": ["well-respected", "sustainability efforts", "environmental responsibility", "operational efficiency", "crew safety"], "Lack of Objectivity": ["suggest that the company is not only concerned with environmental responsibility but also operational efficiency and crew safety"], "Authority Bias": ["well-respected"], "Information Bias": ["According to public records"], "Selection Bias": ["These investments suggest"], "Presentation Bias": ["The company also conducted a number of transactions during this time period"], "Confirmation Bias": ["The company is not only concerned with environmental responsibility but also operational efficiency and crew safety"]}